vuba/__init__.py
vuba/gui.py
vuba/imio.py
vuba/ops.py
vuba-0.2.9.2.dist-info/LICENSE
vuba-0.2.9.2.dist-info/METADATA
vuba-0.2.9.2.dist-info/WHEEL
vuba-0.2.9.2.dist-info/top_level.txt
vuba-0.2.9.2.dist-info/RECORD
