Metadata-Version: 2.1
Name: vuba
Version: 0.2.9.2
Summary: An easy to use library for constructing OpenCV HighGUI interfaces.
Home-page: https://github.com/EmbryoPhenomics/vuba
Author: Ziad Ibbini
Author-email: ziad.ibbini@students.plymouth.ac.uk
License: MIT
Project-URL: Source, https://github.com/EmbryoPhenomics/vuba/tree/main/vuba
Platform: UNKNOWN
Requires-Python: >=3.5, <4
Requires-Dist: dataclasses
Requires-Dist: more-itertools
Requires-Dist: natsort
Requires-Dist: numpy
Requires-Dist: opencv-python
Requires-Dist: tqdm
